pilk/SilkDecoder.py
pilk/SilkEncoder.py
pilk/__init__.py
pilk/_pilk.cp36-win_amd64.pyd
pilk/_pilk.pyi
pilk-0.2.4.dist-info/LICENSE
pilk-0.2.4.dist-info/METADATA
pilk-0.2.4.dist-info/WHEEL
pilk-0.2.4.dist-info/top_level.txt
pilk-0.2.4.dist-info/RECORD
