Metadata-Version: 2.1
Name: pilk
Version: 0.2.4
Summary: python silk voice library
Home-page: https://github.com/foyoux/pilk
Author: foyou
Author-email: yimi.0822@qq.com
Maintainer: foyou
Maintainer-email: yimi.0822@qq.com
License: UNKNOWN
Download-URL: https://github.com/foyoux/pilk/releases
Keywords: silk,voice,python,extension,wechat,qq,tencent,xposed,c/c++
Platform: UNKNOWN
Classifier: Development Status :: 4 - Beta
Classifier: License :: OSI Approved :: GNU General Public License v3 (GPLv3)
Classifier: Intended Audience :: End Users/Desktop
Classifier: Natural Language :: Chinese (Simplified)
Classifier: Operating System :: Microsoft :: Windows
Classifier: Operating System :: POSIX
Classifier: Programming Language :: C
Classifier: Programming Language :: Python
Classifier: Programming Language :: Python :: 3
Classifier: Programming Language :: Python :: 3.6
Classifier: Programming Language :: Python :: 3.7
Classifier: Programming Language :: Python :: 3.8
Classifier: Programming Language :: Python :: 3.9
Classifier: Programming Language :: Python :: 3.10
Classifier: Programming Language :: Python :: 3.11
Classifier: Topic :: Multimedia :: Sound/Audio
Requires-Python: >=3.6
License-File: LICENSE
Requires-Dist: typing-extensions
